KitronikAirQualityControlHAT.py
KitronikAirQualityControlHAT-1.0.9.dist-info/LICENSE
KitronikAirQualityControlHAT-1.0.9.dist-info/METADATA
KitronikAirQualityControlHAT-1.0.9.dist-info/WHEEL
KitronikAirQualityControlHAT-1.0.9.dist-info/top_level.txt
KitronikAirQualityControlHAT-1.0.9.dist-info/RECORD
