Metadata-Version: 2.1
Name: KitronikAirQualityControlHAT
Version: 1.0.9
Summary: Kitronik Raspberry Pi HAT for monitoring Air Quality
Requires-Python: >=3.7
License-File: LICENSE
